gif_converter_nk/__init__.py
gif_converter_nk/gif_converter.py
gif_converter_nk-1.0.0.dist-info/LICENSE
gif_converter_nk-1.0.0.dist-info/METADATA
gif_converter_nk-1.0.0.dist-info/WHEEL
gif_converter_nk-1.0.0.dist-info/top_level.txt
gif_converter_nk-1.0.0.dist-info/RECORD
